bikeride/__init__.py
bikeride/bikeride.py
bikeride/knmi.py
bikeride/oikolab.py
bikeride/plot.py
bikeride/weather.py
pybikeride-0.0.7.dist-info/METADATA
pybikeride-0.0.7.dist-info/WHEEL
pybikeride-0.0.7.dist-info/top_level.txt
pybikeride-0.0.7.dist-info/RECORD
