Metadata-Version: 2.2
Name: pybikeride
Version: 0.0.7
Summary: Analyse and plot gps files of bicycle rides
Author-email: dirkmjk <info@dirkmjk.nl>
Project-URL: Homepage, https://codeberg.org/dirkmjk/bikeride
Keywords: cycling,gps,gpx,fit,garmin
Classifier: License :: OSI Approved :: MIT License
Classifier: Programming Language :: Python
Classifier: Programming Language :: Python :: 3
Requires-Dist: python-dateutil
Requires-Dist: pandas
Requires-Dist: numpy
Requires-Dist: geopy
Requires-Dist: fitdecode
Requires-Dist: bs4
Requires-Dist: ipyleaflet
Requires-Dist: requests
